<?xml version="1.0"?>
<block>
  <name>Interference Energy Detector</name>
  <key>lsa_interference_energy_detector_cc</key>
  <category>[lsa]</category>
  <import>import lsa</import>
  <make>lsa.interference_energy_detector_cc($ed_tagname, $voe_tagname,  $ed_thres, $voe_thres,$blocklength,$mode,$debug)</make>
  <!-- Make one 'param' node for every Parameter you want settable from the GUI.
       Sub-nodes:
       * name
       * key (makes the value accessible as $keyname, e.g. in the make node)
       * type -->
  <param>
    <name>Energy Tagname</name>
    <key>ed_tagname</key>
    <value>"energy_tag"</value>
    <type>string</type> 
  </param>

  <param>
    <name>Variance of Energy Tagname</name>
    <key>voe_tagname</key>
    <value>"interference_tag"</value>
    <type>string</type>
  </param>
  <param>
    <name>ED threshold(dB)</name>
    <key>ed_thres</key>
    <type>float</type>
  </param>
  <param>
    <name>VoE threshold(dB)</name>
    <key>voe_thres</key>
    <type>float</type>
  </param>
  <param>
    <name>Blocklength</name>
    <key>blocklength</key>
    <type>int</type>
  </param>
  <param>
    <name>Mode</name>
    <key>mode</key>
    <value>0</value>
    <type>int</type>
      <option>
        <name>Block</name>
        <key>0</key>
      </option>
      <option>
        <name>Sliding window</name>
        <key>1</key>
      </option>
  </param>
  <param>
    <name>Debug</name>
    <key>debug</key>
    <value>False</value>
    <type>bool</type>
      <option>
        <name>Yes</name>
        <key>True</key>
      </option>
      <option>
        <name>No</name>
        <key>False</key>
      </option>
  </param>
  
  <!-- Make one 'sink' node per input. Sub-nodes:
       * name (an identifier for the GUI)
       * type
       * vlen
       * optional (set to 1 for optional inputs) -->
  <sink>
    <name>in</name>
    <type>complex</type>
  </sink>

  <!-- Make one 'source' node per output. Sub-nodes:
       * name (an identifier for the GUI)
       * type
       * vlen
       * optional (set to 1 for optional inputs) -->
  <source>
    <name>out</name>
    <type>complex</type>
  </source>
  <source>
    <name>ED</name>
    <type>float</type>
    <optional>1</optional>
  </source>
  <source>
    <name>debug</name>
    <type>message</type>
    <optional>1</optional>
  </source>
  
</block>
